odoo/addons/account_statement_import_move_line/README.rst
odoo/addons/account_statement_import_move_line/__init__.py
odoo/addons/account_statement_import_move_line/__manifest__.py
odoo/addons/account_statement_import_move_line/i18n/account_bank_statement_import_move_line.pot
odoo/addons/account_statement_import_move_line/i18n/account_statement_import_move_line.pot
odoo/addons/account_statement_import_move_line/i18n/de.po
odoo/addons/account_statement_import_move_line/i18n/es.po
odoo/addons/account_statement_import_move_line/i18n/fr.po
odoo/addons/account_statement_import_move_line/i18n/hr.po
odoo/addons/account_statement_import_move_line/i18n/it.po
odoo/addons/account_statement_import_move_line/i18n/nl.po
odoo/addons/account_statement_import_move_line/i18n/pt_BR.po
odoo/addons/account_statement_import_move_line/i18n/pt_PT.po
odoo/addons/account_statement_import_move_line/i18n/sl.po
odoo/addons/account_statement_import_move_line/models/__init__.py
odoo/addons/account_statement_import_move_line/models/account_move_line.py
odoo/addons/account_statement_import_move_line/readme/CONFIGURE.rst
odoo/addons/account_statement_import_move_line/readme/CONTRIBUTORS.rst
odoo/addons/account_statement_import_move_line/readme/DESCRIPTION.rst
odoo/addons/account_statement_import_move_line/readme/USAGE.rst
odoo/addons/account_statement_import_move_line/security/ir.model.access.csv
odoo/addons/account_statement_import_move_line/static/description/icon.png
odoo/addons/account_statement_import_move_line/static/description/index.html
odoo/addons/account_statement_import_move_line/tests/__init__.py
odoo/addons/account_statement_import_move_line/tests/test_account_bank_statement_import_move_line.py
odoo/addons/account_statement_import_move_line/views/account_bank_statement_view.xml
odoo/addons/account_statement_import_move_line/wizards/__init__.py
odoo/addons/account_statement_import_move_line/wizards/account_statement_line_create.py
odoo14_addon_account_statement_import_move_line-14.0.1.0.1.dev11.dist-info/METADATA
odoo14_addon_account_statement_import_move_line-14.0.1.0.1.dev11.dist-info/WHEEL
odoo14_addon_account_statement_import_move_line-14.0.1.0.1.dev11.dist-info/top_level.txt
odoo14_addon_account_statement_import_move_line-14.0.1.0.1.dev11.dist-info/RECORD
